[
    {
        "id": 1,
        "name": "Nigerian Oil",
        "price": 7000,
        "image": "assets/img/p1.avif"
    },
    {
        "id": 2,
        "name": "Organic Oil",
        "price": 14500,
        "image": "assets/img/p2.avif"
    },
    {
        "id": 3,
        "name": "Elsa Ointment",
        "price": 12900,
        "image": "assets/img/p3.avif"
    },
    {
        "id": 4,
        "name": "ILCE-7M2",
        "price": 3000,
        "image": "assets/img/p4.avif"
    },
    {
        "id": 5,
        "name": "Cocooil",
        "price": 2500,
        "image": "assets/img/p5.avif"
    },
    {
        "id": 6,
        "name": "Natural X",
        "price": 6000,
        "image": "assets/img/p6.avif"
    }
]